{"cookies": [{"name": "visitor_id", "value": "JB0PSFK7PR04XT68Z269S78XTRPF60I7", "domain": "supplier.getyourguide.com", "path": "/", "expires": -1, "httpOnly": true, "secure": true, "sameSite": "Lax"}, {"name": "supplier_locale_code", "value": "en-US", "domain": "supplier.getyourguide.com", "path": "/", "expires": -1, "httpOnly": false, "secure": true, "sameSite": "Lax"}, {"name": "is_embedded", "value": "false", "domain": "supplier.getyourguide.com", "path": "/", "expires": -1, "httpOnly": false, "secure": false, "sameSite": "Lax"}, {"name": "_hjSessionUser_1199376", "value": "eyJpZCI6IjA1MWEyMzlhLWIyYTktNWM3ZC1iZDliLTViNTE3ZmMwZGEwYSIsImNyZWF0ZWQiOjE3Nzg2NDE1NjQzNzcsImV4aXN0aW5nIjp0cnVlfQ==", "domain": ".getyourguide.com", "path": "/", "expires": 1810302253, "httpOnly": false, "secure": true, "sameSite": "None"}, {"name": "sport_vertical_nav", "value": "sidebar-nav", "domain": "supplier.getyourguide.com", "path": "/", "expires": 1779246366.015277, "httpOnly": false, "secure": false, "sameSite": "Lax"}, {"name": "supplier_id", "value": "734946", "domain": "supplier.getyourguide.com", "path": "/", "expires": -1, "httpOnly": false, "secure": false, "sameSite": "Lax"}, {"name": "_iidt", "value": "NxFDiJLny8ZuvSRUp1gySRrrm7I9ieDZTsMDCyq1n7pTcGVdAIX2UaS3nPa6h7nwhDJ4vW4lrlgfVlMGZ3s4hwjZlto6aEuHxjdxy4EIhsy06UXvkA==", "domain": ".withpersona.com", "path": "/", "expires": 1810177604.906777, "httpOnly": true, "secure": true, "sameSite": "None"}, {"name": "ab.storage.deviceId.c36da9fe-8874-4c02-8a45-d9edace47cff", "value": "g%3Aabfb949a-ec11-a6c2-3e94-1204da2d30ef%7Ce%3Aundefined%7Cc%3A1778641575743%7Cl%3A1778761651905", "domain": ".getyourguide.com", "path": "/", "expires": 1813326253, "httpOnly": false, "secure": false, "sameSite": "Lax"}, {"name": "ab.storage.userId.c36da9fe-8874-4c02-8a45-d9edace47cff", "value": "g%3A1071808%7Ce%3Aundefined%7Cc%3A1778641603162%7Cl%3A1778761651905", "domain": ".getyourguide.com", "path": "/", "expires": 1813326253, "httpOnly": false, "secure": false, "sameSite": "Lax"}, {"name": "_hjSession_1199376", "value": "eyJpZCI6ImQ5YTMyMDQ0LWJjNDMtNDM4OS04NGUyLWY2M2FmYWU3NWE3MSIsImMiOjE3Nzg3NjU4MDQ3MjcsInMiOjAsInIiOjAsInNiIjowLCJzciI6MCwic2UiOjAsImZzIjowLCJzcCI6MH0=", "domain": ".getyourguide.com", "path": "/", "expires": 1778767896, "httpOnly": false, "secure": true, "sameSite": "None"}, {"name": "__cf_bm", "value": "dBE74t7Xx4UAm.cE8pDev4zTh_JGZ0FuRjBMQ9SgGnA-1778766053.6936858-1.0.1.1-FZoqrS5Q1Uq2aWxLaMwEUj_qM4GawyPGKczYV9ctAAMuP5suZwa6CEekonuhMM.qLcqWJ3dTOC81RuSi2RxHgQjTZXtd_S4_snu0mMQVq2dwNE.B8fXMcgkSImq4Avr9", "domain": ".supplier.getyourguide.com", "path": "/", "expires": 1778767854.525078, "httpOnly": true, "secure": true, "sameSite": "None"}, {"name": "__cf_bm", "value": "6nELOyQN8PNrntGqI5MtbDZT3auHr77iGimBr9nwkyM-1778766062.5036712-1.0.1.1-ZL1AgveiU8fqHZeAQGRtPNECGyI7Wz0wT67KX.9h1i.vbWiqpg9miZwFFiIXkIMw.o5EYFDD8rFNx7K36wKC6F9Jqaz4_CpdtKbdt.91oQSrFE6qZy3DsABLOjN_frAZ", "domain": ".travelers-api.getyourguide.com", "path": "/", "expires": 1778767862.676154, "httpOnly": true, "secure": true, "sameSite": "None"}, {"name": "__cf_bm", "value": "rbcz9jfZweP8BhOIPSyW5eAXAaSeDTGpaLrRrKzL0QU-1778766107-1.0.1.1-lmupXvVA_m4ywN3d2k1vUThL.zgtuLdrd75uK0v4A8oZPzX4t93pwtwVe04_JrKCXujwLcZp9DO_yTKjE3SFGhKnux8o5Ax3FYkIgeYc1kHjPbprQTGiNFNNJjpzvrlI", "domain": ".zendesk.com", "path": "/", "expires": 1778767907.244888, "httpOnly": true, "secure": true, "sameSite": "None"}, {"name": "_cfuvid", "value": "AFqvpe2JbfToDD5pg95QIpgBCIoSLhhsBUZJqi5V310-1778766107234-0.0.1.1-604800000", "domain": ".zendesk.com", "path": "/", "expires": -1, "httpOnly": true, "secure": true, "sameSite": "None"}, {"name": "apVId", "value": "tt55c6q29jll8u7c4zr34thkp6lldeti", "domain": "supplier.getyourguide.com", "path": "/", "expires": -1, "httpOnly": false, "secure": true, "sameSite": "Lax"}, {"name": "ab.storage.sessionId.c36da9fe-8874-4c02-8a45-d9edace47cff", "value": "g%3A1a6a4370-a0c6-2de4-4332-6d794f4525e1%7Ce%3A1778768053681%7Cc%3A1778761651904%7Cl%3A1778766253681", "domain": ".getyourguide.com", "path": "/", "expires": 1813326253, "httpOnly": false, "secure": false, "sameSite": "Lax"}, {"name": "_dd_s", "value": "aid=d433ae05-d5d0-4f63-8cd7-bcb32c8533e4&rum=0&expire=1778767185181", "domain": "supplier.getyourguide.com", "path": "/", "expires": 1810302285, "httpOnly": false, "secure": false, "sameSite": "Strict"}], "origins": [{"origin": "https://supplier.getyourguide.com", "localStorage": [{"name": "ab.storage.triggers.c36da9fe-8874-4c02-8a45-d9edace47cff", "value": "{\"v\":[]}"}, {"name": "ab.storage.userId.c36da9fe-8874-4c02-8a45-d9edace47cff", "value": "{\"v\":\"g:1071808|e:undefined|c:1778641603162|l:1778761651905\"}"}, {"name": "ab.storage.device.c36da9fe-8874-4c02-8a45-d9edace47cff", "value": "{\"v\":{\"browser\":\"Chrome\",\"browser_version\":\"147\",\"os_version\":\"Windows\",\"locale\":\"en-us\",\"time_zone\":\"UTC\",\"user_agent\":\"Mozilla/5.0 (Windows NT 10.0; Win64; x64) AppleWebKit/537.36 (KHTML, like Gecko) Chrome/120.0.0.0 Safari/537.36\"}}"}, {"name": "statsig.cached.evaluations.3724929477", "value": "{\"source\":\"NetworkNotModified\",\"data\":\"{\\\"feature_gates\\\":{\\\"1175204692\\\":{\\\"name\\\":\\\"1175204692\\\",\\\"value\\\":false,\\\"rule_id\\\":\\\"default\\\",\\\"id_type\\\":\\\"supplierId\\\",\\\"secondary_exposures\\\":[]},\\\"1357805670\\\":{\\\"name\\\":\\\"1357805670\\\",\\\"value\\\":false,\\\"rule_id\\\":\\\"1roFVFlnaR2vBKPULmVQUJ:0.00:1\\\",\\\"id_type\\\":\\\"supplierId\\\",\\\"secondary_exposures\\\":[]},\\\"1761599886\\\":{\\\"name\\\":\\\"1761599886\\\",\\\"value\\\":false,\\\"rule_id\\\":\\\"default\\\",\\\"id_type\\\":\\\"userID\\\",\\\"secondary_exposures\\\":[]},\\\"2259178277\\\":{\\\"name\\\":\\\"2259178277\\\",\\\"value\\\":false,\\\"rule_id\\\":\\\"default\\\",\\\"id_type\\\":\\\"userID\\\",\\\"secondary_exposures\\\":[]},\\\"3001222149\\\":{\\\"name\\\":\\\"3001222149\\\",\\\"value\\\":false,\\\"rule_id\\\":\\\"default\\\",\\\"id_type\\\":\\\"supplierId\\\",\\\"secondary_exposures\\\":[]},\\\"3505488071\\\":{\\\"name\\\":\\\"3505488071\\\",\\\"value\\\":false,\\\"rule_id\\\":\\\"64SJzxd8T6JiV9V97bwvMf\\\",\\\"id_type\\\":\\\"supplierId\\\",\\\"secondary_exposures\\\":[]},\\\"3902645057\\\":{\\\"name\\\":\\\"3902645057\\\",\\\"value\\\":false,\\\"rule_id\\\":\\\"default\\\",\\\"id_type\\\":\\\"supplierId\\\",\\\"secondary_exposures\\\":[]}},\\\"dynamic_configs\\\":{\\\"1051049071\\\":{\\\"name\\\":\\\"1051049071\\\",\\\"value\\\":{},\\\"rule_id\\\":\\\"inlineTargetingRules\\\",\\\"group\\\":\\\"inlineTargetingRules\\\",\\\"is_device_based\\\":false,\\\"id_type\\\":\\\"userID\\\",\\\"is_experiment_active\\\":true,\\\"is_user_in_experiment\\\":false,\\\"secondary_exposures\\\":[]},\\\"1311810217\\\":{\\\"name\\\":\\\"1311810217\\\",\\\"value\\\":{},\\\"rule_id\\\":\\\"prestart\\\",\\\"group\\\":\\\"prestart\\\",\\\"is_device_based\\\":false,\\\"id_type\\\":\\\"supplierId\\\",\\\"is_experiment_active\\\":false,\\\"is_user_in_experiment\\\":false,\\\"secondary_exposures\\\":[]},\\\"3956400110\\\":{\\\"name\\\":\\\"3956400110\\\",\\\"value\\\":{},\\\"rule_id\\\":\\\"prestart\\\",\\\"group\\\":\\\"prestart\\\",\\\"is_device_based\\\":false,\\\"id_type\\\":\\\"userID\\\",\\\"is_experiment_active\\\":false,\\\"is_user_in_experiment\\\":false,\\\"secondary_exposures\\\":[]}},\\\"layer_configs\\\":{},\\\"sdkParams\\\":{},\\\"has_updates\\\":true,\\\"generator\\\":\\\"scrapi-nest\\\",\\\"time\\\":1778656519663,\\\"company_lcut\\\":1778656519663,\\\"evaluated_keys\\\":{\\\"userID\\\":\\\"JB0PSFK7PR04XT68Z269S78XTRPF60I7\\\",\\\"stableID\\\":\\\"468e9412-681b-4536-8e9a-6f5bdc35d66d\\\"},\\\"hash_used\\\":\\\"djb2\\\",\\\"derived_fields\\\":{\\\"ip\\\":\\\"20.168.110.178\\\",\\\"country\\\":\\\"US\\\",\\\"locale\\\":\\\"en-US\\\",\\\"browserName\\\":\\\"Chrome\\\",\\\"browserVersion\\\":\\\"120.0.0\\\",\\\"osName\\\":\\\"Windows\\\",\\\"osVersion\\\":\\\"10.0.0\\\",\\\"browser_name\\\":\\\"Chrome\\\",\\\"browser_version\\\":\\\"120.0.0\\\",\\\"os_name\\\":\\\"Windows\\\",\\\"os_version\\\":\\\"10.0.0\\\"},\\\"hashed_sdk_key_used\\\":\\\"1729579267\\\",\\\"can_record_session\\\":false,\\\"recording_blocked\\\":false,\\\"session_recording_rate\\\":1,\\\"auto_capture_settings\\\":{\\\"disabled_events\\\":{\\\"page_view\\\":true,\\\"page_view_end\\\":true,\\\"click\\\":true,\\\"scroll\\\":true,\\\"session_start\\\":true,\\\"form_submit\\\":true,\\\"error\\\":true,\\\"dead_click\\\":true,\\\"rage_click\\\":true,\\\"copy\\\":true}},\\\"param_stores\\\":{},\\\"target_app_used\\\":\\\"supplier-portal\\\",\\\"full_checksum\\\":\\\"4010428338\\\",\\\"is_delta\\\":true,\\\"checksum\\\":\\\"2542090376\\\",\\\"checksumV2\\\":\\\"1192247432\\\",\\\"deltas_full_response\\\":null}\",\"receivedAt\":1778766056861,\"stableID\":\"468e9412-681b-4536-8e9a-6f5bdc35d66d\",\"fullUserHash\":\"3874365612\"}"}, {"name": "66d0858efe670c71fc7df867.clientId", "value": "147d4cf90a394a3086794cf9b90e9d26"}, {"name": "statsig.stable_id.3726937202", "value": "\"468e9412-681b-4536-8e9a-6f5bdc35d66d\""}, {"name": "ab.storage.messagingSessionStart.c36da9fe-8874-4c02-8a45-d9edace47cff", "value": "{\"v\":1778752761905}"}, {"name": "ZD-suid", "value": "{\"id\":\"cc8b219994b5414ba733c9f8b3dfb310\",\"expiry\":1778767153910,\"tabs\":{\"count\":2,\"expiry\":0}}"}, {"name": "ab.storage.requestAttempts.c36da9fe-8874-4c02-8a45-d9edace47cff", "value": "{\"v\":{\"d\":1,\"ff\":1}}"}, {"name": "ab.storage.sessionId.c36da9fe-8874-4c02-8a45-d9edace47cff", "value": "{\"v\":\"g:1a6a4370-a0c6-2de4-4332-6d794f4525e1|e:1778768053681|c:1778761651904|l:1778766253681\"}"}, {"name": "isZendeskScriptLoaded", "value": "true"}, {"name": "ucData", "value": "{\"gcm\":{\"adsDataRedaction\":true,\"adStorage\":\"denied\",\"adPersonalization\":\"denied\",\"adUserData\":\"denied\",\"analyticsStorage\":\"denied\"},\"consent\":{\"services\":{\"Xl0HIOViY\":{\"name\":\"Datadog Real User Monitoring\",\"consent\":true},\"HkPBYFofN\":{\"name\":\"Google Fonts\",\"consent\":true},\"R2gyvn3ugawW0t\":{\"name\":\"Google Hosted Libraries\",\"consent\":true},\"S1pcEj_jZX\":{\"name\":\"Google Maps\",\"consent\":true},\"XJGT8f-58\":{\"name\":\"Google Sign-In\",\"consent\":true},\"BJ59EidsWQ\":{\"name\":\"Google Tag Manager\",\"consent\":true},\"rJJjcVouoZ7\":{\"name\":\"gstatic.com\",\"consent\":true},\"H1Vl5NidjWX\":{\"name\":\"Usercentrics Consent Management Platform\",\"consent\":true},\"54s8nFgf\":{\"name\":\"Zendesk\",\"consent\":true},\"ko1w5PpFl\":{\"name\":\"Facebook Pixel\",\"consent\":false},\"twMyStLkn\":{\"name\":\"Google Ads Conversion Tracking\",\"consent\":false},\"87JYasXPF\":{\"name\":\"Google Analytics 4\",\"consent\":false},\"S1kgcNo_j-m\":{\"name\":\"Hotjar\",\"consent\":false},\"JQ2XQxIk\":{\"name\":\"LinkedIn Insight Tag\",\"consent\":false},\"rH1vNPCFR\":{\"name\":\"Sentry\",\"consent\":false}}},\"ui\":{\"language\":\"en\"}}"}, {"name": "ab.storage.ffLastRefreshAt.c36da9fe-8874-4c02-8a45-d9edace47cff", "value": "{\"v\":1778761652284}"}, {"name": "ZD-buid", "value": "147d4cf90a394a3086794cf9b90e9d26"}, {"name": "isZendeskChatAuthenticated", "value": "true"}, {"name": "zendeskAuthToken", "value": "eyJhbGciOiJIUzUxMiIsInR5cCI6IkpXVCIsImtpZCI6ImFwcF82NmQ4NTIzOWM1NzkwMzhlYzYxZGYwOTEifQ.eyJzY29wZSI6InVzZXIiLCJleHRlcm5hbF9pZCI6IkdZR1NVUFBMSUVSQUNDT1VOVDEwNzE4MDgiLCJlbWFpbF92ZXJpZmllZCI6dHJ1ZSwiaWF0IjoxNzc4NzY2MjUzLCJqdGkiOiJlNzRiMGIwZi02MTYwLTRhY2YtOTRmOC04YmJmYTI0NGNjYTIiLCJuYW1lIjoiTmlsZSBDcnlzdGFsIiwiZW1haWwiOiJuaWxlLmNyeXN0YWwuYm9va2luZ0BnbWFpbC5jb20ifQ.F6oLitM0KyFQC2V7ihpikzMszM0_OkUHdteZFgk3NkLuQWyuh7sHp9_YFgiPgMOu8pAKcZ0XSWg7nIwkBXF7cw"}, {"name": "zendeskChatStatus", "value": "unknown"}, {"name": "sentinel_data_obj_sent", "value": "{\"734946\":true}"}, {"name": "66d0858efe670c71fc7df867.appUserId", "value": "69c466fc4b23483749e0f871"}, {"name": "statsig.last_modified_time.evaluations", "value": "{\"statsig.cached.evaluations.3724929477\":1778766056861,\"statsig.cached.evaluations.587077486\":1778766253279}"}, {"name": "66d0858efe670c71fc7df867.surname", "value": "Crystal"}, {"name": "66d0858efe670c71fc7df867.conversationStartedAt", "value": "\"2026-05-14T13:44:15.176Z\""}, {"name": "ab.storage.lastReqToEndpoint.c36da9fe-8874-4c02-8a45-d9edace47cff", "value": "{\"v\":{\"d\":1778766253682,\"ff\":1778761651913}}"}, {"name": "ab.storage.session_id_for_cached_metadata.c36da9fe-8874-4c02-8a45-d9edace47cff", "value": "{\"v\":\"1a6a4370-a0c6-2de4-4332-6d794f4525e1\"}"}, {"name": "statsig.cached.evaluations.587077486", "value": "{\"source\":\"NetworkNotModified\",\"data\":\"{\\\"feature_gates\\\":{\\\"1175204692\\\":{\\\"name\\\":\\\"1175204692\\\",\\\"value\\\":false,\\\"rule_id\\\":\\\"default\\\",\\\"id_type\\\":\\\"supplierId\\\",\\\"secondary_exposures\\\":[]},\\\"1357805670\\\":{\\\"name\\\":\\\"1357805670\\\",\\\"value\\\":false,\\\"rule_id\\\":\\\"1roFVFlnaR2vBKPULmVQUJ:0.00:1\\\",\\\"id_type\\\":\\\"supplierId\\\",\\\"secondary_exposures\\\":[]},\\\"1761599886\\\":{\\\"name\\\":\\\"1761599886\\\",\\\"value\\\":false,\\\"rule_id\\\":\\\"default\\\",\\\"id_type\\\":\\\"userID\\\",\\\"secondary_exposures\\\":[]},\\\"2259178277\\\":{\\\"name\\\":\\\"2259178277\\\",\\\"value\\\":false,\\\"rule_id\\\":\\\"default\\\",\\\"id_type\\\":\\\"userID\\\",\\\"secondary_exposures\\\":[]},\\\"3001222149\\\":{\\\"name\\\":\\\"3001222149\\\",\\\"value\\\":false,\\\"rule_id\\\":\\\"default\\\",\\\"id_type\\\":\\\"supplierId\\\",\\\"secondary_exposures\\\":[]},\\\"3505488071\\\":{\\\"name\\\":\\\"3505488071\\\",\\\"value\\\":false,\\\"rule_id\\\":\\\"64SJzxd8T6JiV9V97bwvMf\\\",\\\"id_type\\\":\\\"supplierId\\\",\\\"secondary_exposures\\\":[]},\\\"3902645057\\\":{\\\"name\\\":\\\"3902645057\\\",\\\"value\\\":false,\\\"rule_id\\\":\\\"default\\\",\\\"id_type\\\":\\\"supplierId\\\",\\\"secondary_exposures\\\":[]}},\\\"dynamic_configs\\\":{\\\"1051049071\\\":{\\\"name\\\":\\\"1051049071\\\",\\\"value\\\":{},\\\"rule_id\\\":\\\"inlineTargetingRules\\\",\\\"group\\\":\\\"inlineTargetingRules\\\",\\\"is_device_based\\\":false,\\\"id_type\\\":\\\"userID\\\",\\\"is_experiment_active\\\":true,\\\"is_user_in_experiment\\\":false,\\\"secondary_exposures\\\":[]},\\\"1311810217\\\":{\\\"name\\\":\\\"1311810217\\\",\\\"value\\\":{},\\\"rule_id\\\":\\\"prestart\\\",\\\"group\\\":\\\"prestart\\\",\\\"is_device_based\\\":false,\\\"id_type\\\":\\\"supplierId\\\",\\\"is_experiment_active\\\":false,\\\"is_user_in_experiment\\\":false,\\\"secondary_exposures\\\":[]},\\\"3956400110\\\":{\\\"name\\\":\\\"3956400110\\\",\\\"value\\\":{},\\\"rule_id\\\":\\\"prestart\\\",\\\"group\\\":\\\"prestart\\\",\\\"is_device_based\\\":false,\\\"id_type\\\":\\\"userID\\\",\\\"is_experiment_active\\\":false,\\\"is_user_in_experiment\\\":false,\\\"secondary_exposures\\\":[]}},\\\"layer_configs\\\":{},\\\"sdkParams\\\":{},\\\"has_updates\\\":true,\\\"generator\\\":\\\"scrapi-nest\\\",\\\"time\\\":1778655337918,\\\"company_lcut\\\":1778655337918,\\\"evaluated_keys\\\":{\\\"userID\\\":\\\"JB0PSFK7PR04XT68Z269S78XTRPF60I7\\\",\\\"stableID\\\":\\\"468e9412-681b-4536-8e9a-6f5bdc35d66d\\\",\\\"customIDs\\\":{\\\"supplierId\\\":\\\"734946\\\"}},\\\"hash_used\\\":\\\"djb2\\\",\\\"derived_fields\\\":{\\\"ip\\\":\\\"4.236.166.151\\\",\\\"country\\\":\\\"US\\\",\\\"locale\\\":\\\"en-US\\\",\\\"browserName\\\":\\\"Chrome\\\",\\\"browserVersion\\\":\\\"120.0.0\\\",\\\"osName\\\":\\\"Windows\\\",\\\"osVersion\\\":\\\"10.0.0\\\",\\\"browser_name\\\":\\\"Chrome\\\",\\\"browser_version\\\":\\\"120.0.0\\\",\\\"os_name\\\":\\\"Windows\\\",\\\"os_version\\\":\\\"10.0.0\\\"},\\\"hashed_sdk_key_used\\\":\\\"1729579267\\\",\\\"can_record_session\\\":false,\\\"recording_blocked\\\":false,\\\"session_recording_rate\\\":1,\\\"auto_capture_settings\\\":{\\\"disabled_events\\\":{\\\"page_view\\\":true,\\\"page_view_end\\\":true,\\\"click\\\":true,\\\"scroll\\\":true,\\\"session_start\\\":true,\\\"form_submit\\\":true,\\\"error\\\":true,\\\"dead_click\\\":true,\\\"rage_click\\\":true,\\\"copy\\\":true}},\\\"param_stores\\\":{},\\\"target_app_used\\\":\\\"supplier-portal\\\",\\\"full_checksum\\\":\\\"4010428338\\\",\\\"is_delta\\\":true,\\\"checksum\\\":\\\"2542090376\\\",\\\"checksumV2\\\":\\\"1192247432\\\",\\\"deltas_full_response\\\":null}\",\"receivedAt\":1778766253279,\"stableID\":\"468e9412-681b-4536-8e9a-6f5bdc35d66d\",\"fullUserHash\":\"4194087611\"}"}, {"name": "66d0858efe670c71fc7df867.email", "value": "nile.crystal.booking@gmail.com"}, {"name": "ab.storage.globalRateLimitCurrentTokenCount.c36da9fe-8874-4c02-8a45-d9edace47cff", "value": "{\"v\":13}"}, {"name": "ab.storage.sdk_metadata.c36da9fe-8874-4c02-8a45-d9edace47cff", "value": "{\"v\":[\"npm\"]}"}, {"name": "statsig.network_fallback.1729579267", "value": "{\"rgstr\":{\"urlConfigChecksum\":\"2021908170\",\"url\":\"https://statsig.getyourguide.com/v1/rgstr\",\"expiryTime\":1779371053620,\"previous\":[]}}"}, {"name": "ab.storage.deviceId.c36da9fe-8874-4c02-8a45-d9edace47cff", "value": "{\"v\":\"g:abfb949a-ec11-a6c2-3e94-1204da2d30ef|e:undefined|c:1778641575743|l:1778761651905\"}"}, {"name": "ucString", "value": "N4IgbgpgTgzglgewHYgFwEYA0ICucBq08yaIAzAHTroCcFADCNgMbIAuUCANl9AJIATUgCYAhsIEB2MhABmAI1Hphs0fJoQaw+ugAsADn3zJANhPyBJjaOYmArCfSS7ZK0YOzJzSybLoB6HZ2umSikkwgXKJIAOY4ojEQpBAo2DAQbGxwsWigbACeAA5JqCAA4gAiAAoAShFwQqXyMIVIALQAGgC2AIIAmggAHl0wAFIRkLCIKKVOFJIUZDQgAL7YOIUComwQAj1saE6S+ia6gZLCNLrC65vbuwBC+aTIFSn5PTwAytBgcMwQGARZhQCD3PYHDCSY6nQKnMj0OzYUEARzwoMaqi46TSbG2OCBpR6ABliQB9CoAUQAcnxKRUIgViqRKR0qsS+ABhPgAFQiAAtRDB+aRRCYBMJrgIBPREQCILo7OgTEZhPJLsx1HZocxtCZmAbmJINOhREqTnoBCcyMIIPJ5DpxMI7Ms0r9/hBBISANoAXWwMUKzC+cBiSFEXDQWJxIGyOygNiyJFKBOgqyAA="}, {"name": "ab.storage.lastSdkReq.c36da9fe-8874-4c02-8a45-d9edace47cff", "value": "{\"v\":1778766253682}"}, {"name": "ab.storage.serverConfig.c36da9fe-8874-4c02-8a45-d9edace47cff", "value": "{\"v\":{\"s\":\"5.1.1\",\"l\":1774361172,\"e\":[],\"a\":[\"20250129_commission_is_tour_6\",\"202501_activ_tours_3defects_campaign\",\"accounts\",\"attributesMap\",\"completedness\",\"dev_tours\",\"exampleArr\",\"exampleArr10\",\"exampleArr2\",\"mql_activities>tours_online\"],\"p\":[],\"m\":21600,\"v\":\"BGWjRIY5UQ_emQBXbcJdUyrKz0N2vDTT_DuZQbnoHe6E6gTIA9m6un60Y-X3Ip0ifxBHjK7oPoHiodrrZwMXr9c=\",\"c\":{\"enabled\":true},\"f\":{\"enabled\":true,\"refresh_rate_limit\":300},\"grl\":{\"capacity\":30,\"enabled\":true,\"endpoint_overrides\":{\"banners/sync\":{\"capacity\":5,\"refill_rate\":180},\"content_cards/sync\":{\"capacity\":5,\"refill_rate\":10},\"push/redeliver\":{\"capacity\":1,\"refill_rate\":180}},\"refill_rate\":30}}}"}, {"name": "zendeskExternalId", "value": "GYGSUPPLIERACCOUNT1071808"}, {"name": "ab.storage.ff.sessionId.c36da9fe-8874-4c02-8a45-d9edace47cff", "value": "{\"v\":\"1a6a4370-a0c6-2de4-4332-6d794f4525e1\"}"}, {"name": "sidebar-onboarding-seen", "value": "true"}, {"name": "uc:analytics:firedEvents:bspn-XmAYoxmsJ", "value": "[\"CMP_ELIGIBLE\",\"CMP_SHOWN\",\"DENY_ALL\"]"}, {"name": "statsig.session_id.3726937202", "value": "{\"sessionID\":\"da6c2226-410d-469b-9272-e57184a5b39e\",\"startTime\":1778761613816,\"lastUpdate\":1778766253196}"}, {"name": "66d0858efe670c71fc7df867.givenName", "value": "Nile"}, {"name": "ab.storage.ff.c36da9fe-8874-4c02-8a45-d9edace47cff", "value": "{\"v\":{}}"}, {"name": "ab.storage.triggers.ts.c36da9fe-8874-4c02-8a45-d9edace47cff", "value": "{\"v\":1778761652283}"}]}, {"origin": "https://web.cmp.usercentrics.eu", "localStorage": [{"name": "ucData_bspn-XmAYoxmsJ", "value": "{\"ucString\":\"N4IgbgpgTgzglgewHYgFwEYA0ICucBq08yaIAzAHTroCcFADCNgMbIAuUCANl9AJIATUgCYAhsIEB2MhABmAI1Hphs0fJoQaw+ugAsADn3zJANhPyBJjaOYmArCfSS7ZK0YOzJzSybLoB6HZ2umSikkwgXKJIAOY4ojEQpBAo2DAQbGxwsWigbACeAA5JqCAA4gAiAAoAShFwQqXyMIVIALQAGgC2AIIAmggAHl0wAFIRkLCIKKVOFJIUZDQgAL7YOIUComwQAj1saE6S+ia6gZLCNLrC65vbuwBC+aTIFSn5PTwAytBgcMwQGARZhQCD3PYHDCSY6nQKnMj0OzYUEARzwoMaqi46TSbG2OCBpR6ABliQB9CoAUQAcnxKRUIgViqRKR0qsS+ABhPgAFQiAAtRDB+aRRCYBMJrgIBPREQCILo7OgTEZhPJLsx1HZocxtCZmAbmJINOhREqTnoBCcyMIIPJ5DpxMI7Ms0r9/hBBISANoAXWwMUKzC+cBiSFEXDQWJxIGyOygNiyJFKBOgqyAA=\"}"}]}, {"origin": "https://cluster-de.withpersona.com", "localStorage": [{"name": "_vid_t", "value": "rDJr4o0paoxHcPKcvDvoX71bDUDNH1Zkd/9Xaj9QGC4a0nVbRuxIdrZLi30QteJXmmDUqAoCP3lEPisVk0ShJe3k+sfNzmv7RSgybC8Rj9B0q8iMag=="}]}]}