{"cookies": [{"name": "visitor_id", "value": "QVSMG91M55VYJ4BIKBR2N3I1QOWOVP0E", "domain": "supplier.getyourguide.com", "path": "/", "expires": -1, "httpOnly": true, "secure": true, "sameSite": "Lax"}, {"name": "supplier_locale_code", "value": "en-US", "domain": "supplier.getyourguide.com", "path": "/", "expires": -1, "httpOnly": false, "secure": true, "sameSite": "Lax"}, {"name": "is_embedded", "value": "false", "domain": "supplier.getyourguide.com", "path": "/", "expires": -1, "httpOnly": false, "secure": false, "sameSite": "Lax"}, {"name": "_hjSessionUser_1199376", "value": "eyJpZCI6ImY0YmI5MDlkLWQxYWItNTYwOS04YjcwLTA3N2ViNDhmOTY5NyIsImNyZWF0ZWQiOjE3Nzc3OTM0NTg2MzIsImV4aXN0aW5nIjp0cnVlfQ==", "domain": ".getyourguide.com", "path": "/", "expires": 1809339544, "httpOnly": false, "secure": true, "sameSite": "None"}, {"name": "sport_vertical_nav", "value": "sidebar-nav", "domain": "supplier.getyourguide.com", "path": "/", "expires": 1778398259.914857, "httpOnly": false, "secure": false, "sameSite": "Lax"}, {"name": "supplier_id", "value": "734946", "domain": "supplier.getyourguide.com", "path": "/", "expires": -1, "httpOnly": false, "secure": false, "sameSite": "Lax"}, {"name": "_iidt", "value": "hckk7/pCrjVWi4h+TKMQWrNd9HehQ+KBKG/ant3uiWHh5sJ18HZhfmLkJCIYRFvuMK1dvW6YuwXcWE0Z8O19Te7eRTL8JjFBn/atQis89FaWfu1iew==", "domain": ".withpersona.com", "path": "/", "expires": 1809329498.209809, "httpOnly": true, "secure": true, "sameSite": "None"}, {"name": "_hjSession_1199376", "value": "eyJpZCI6IjhmZjNhOTcwLWUxNWMtNGNjMC1iYjk5LTkwYzkwN2Q4MDBjOCIsImMiOjE3Nzc4MDIyMzg4ODcsInMiOjEsInIiOjAsInNiIjowLCJzciI6MCwic2UiOjAsImZzIjowLCJzcCI6MH0=", "domain": ".getyourguide.com", "path": "/", "expires": 1777804079, "httpOnly": false, "secure": true, "sameSite": "None"}, {"name": "ab.storage.deviceId.c36da9fe-8874-4c02-8a45-d9edace47cff", "value": "g%3Ac1b12ea3-b2f2-479f-41bd-329e870e6e00%7Ce%3Aundefined%7Cc%3A1777793469704%7Cl%3A1777802289225", "domain": ".getyourguide.com", "path": "/", "expires": 1812363545, "httpOnly": false, "secure": false, "sameSite": "Lax"}, {"name": "ab.storage.userId.c36da9fe-8874-4c02-8a45-d9edace47cff", "value": "g%3A1071808%7Ce%3Aundefined%7Cc%3A1777793496677%7Cl%3A1777802289225", "domain": ".getyourguide.com", "path": "/", "expires": 1812363545, "httpOnly": false, "secure": false, "sameSite": "Lax"}, {"name": "__cf_bm", "value": "71cKsTgg7R3ieRYwVkFZwNwUt_N_fLrdke9QXhrcY8c-1777803380.1278055-1.0.1.1-auaqOen2XzrrfFyfSXrDfQE6Nqma4hBSvHcF94tok3LKtoaoqT8SLnESntPtkbbn73GzhZlrKrx.e7zfsdYwbwfAmxsoocW3GJmA9nqPXjYivOshCGhfAWq6boVIRymT", "domain": ".supplier.getyourguide.com", "path": "/", "expires": 1777805180.468703, "httpOnly": true, "secure": true, "sameSite": "Lax"}, {"name": "__cf_bm", "value": "dEZTsLImDh7wwsrLNs8kC8puEUE1xY2jQA5CrMq2mog-1777803388.956881-1.0.1.1-sCT8xqgW5csfPLFTk.M6NcGjq5ZLyiz9G7e0WgGiEZHbqeSwxCAA7MmmmnA7zMKulJ84Z3ny2cxMLLekqOjAnFX0yfTriSclKAanNRSSezRFH818uNUnF4vaj1wnDeXh", "domain": ".travelers-api.getyourguide.com", "path": "/", "expires": 1777805189.073639, "httpOnly": true, "secure": true, "sameSite": "Lax"}, {"name": "__cf_bm", "value": "Ho7q46qnjRReq9BgmXUpEeLINyV5k_OPs9.Oqz_zOx0-1777803417-1.0.1.1-KLqSVrLOav28.UUdavJwGAWHQsSiC6NrJc8l.bNCv4wn0lfZ3O6qzwJUTlWPRhs7p7jvvw95RrtH0CuI52.jcm4LRqkpQsSmhYbMhsmgsRl9fwPWYI6TVyxQmBxnWJeT", "domain": ".zendesk.com", "path": "/", "expires": 1777805217.945753, "httpOnly": true, "secure": true, "sameSite": "None"}, {"name": "_cfuvid", "value": "voctEsm2B2eaAjDzG0FwvHyeyxcSNbXeuqw2efr8QhM-1777803417945-0.0.1.1-604800000", "domain": ".zendesk.com", "path": "/", "expires": -1, "httpOnly": true, "secure": true, "sameSite": "None"}, {"name": "apVId", "value": "fd0ehhra104wypunso6mkqtlylbdxe36", "domain": "supplier.getyourguide.com", "path": "/", "expires": -1, "httpOnly": false, "secure": true, "sameSite": "Lax"}, {"name": "ab.storage.sessionId.c36da9fe-8874-4c02-8a45-d9edace47cff", "value": "g%3Af54d535b-3877-9828-1ced-1fac169831dc%7Ce%3A1777805345244%7Cc%3A1777802289225%7Cl%3A1777803545244", "domain": ".getyourguide.com", "path": "/", "expires": 1812363545, "httpOnly": false, "secure": false, "sameSite": "Lax"}, {"name": "_dd_s", "value": "aid=30ccfb0a-e77c-4d9e-9024-8ae8ad8ebc52&rum=0&expire=1777804474980", "domain": "supplier.getyourguide.com", "path": "/", "expires": 1809339574, "httpOnly": false, "secure": false, "sameSite": "Strict"}], "origins": [{"origin": "https://supplier.getyourguide.com", "localStorage": [{"name": "ab.storage.triggers.c36da9fe-8874-4c02-8a45-d9edace47cff", "value": "{\"v\":[]}"}, {"name": "ab.storage.userId.c36da9fe-8874-4c02-8a45-d9edace47cff", "value": "{\"v\":\"g:1071808|e:undefined|c:1777793496677|l:1777802289225\"}"}, {"name": "ab.storage.device.c36da9fe-8874-4c02-8a45-d9edace47cff", "value": "{\"v\":{\"browser\":\"Chrome\",\"browser_version\":\"147\",\"os_version\":\"Windows\",\"locale\":\"en-us\",\"time_zone\":\"UTC\",\"user_agent\":\"Mozilla/5.0 (Windows NT 10.0; Win64; x64) AppleWebKit/537.36 (KHTML, like Gecko) Chrome/120.0.0.0 Safari/537.36\"}}"}, {"name": "66d0858efe670c71fc7df867.clientId", "value": "88925bade3dc4c2a806922c0c2610dc7"}, {"name": "statsig.stable_id.3726937202", "value": "\"eb4947c0-04db-4633-b5bf-efa1fd797600\""}, {"name": "ab.storage.messagingSessionStart.c36da9fe-8874-4c02-8a45-d9edace47cff", "value": "{\"v\":1777793469703}"}, {"name": "ZD-suid", "value": "{\"id\":\"f8967f28745b4486baaba0dda36fe27b\",\"expiry\":1777804445504,\"tabs\":{\"count\":1,\"expiry\":0}}"}, {"name": "ab.storage.requestAttempts.c36da9fe-8874-4c02-8a45-d9edace47cff", "value": "{\"v\":{\"d\":1,\"ff\":1}}"}, {"name": "ab.storage.sessionId.c36da9fe-8874-4c02-8a45-d9edace47cff", "value": "{\"v\":\"g:f54d535b-3877-9828-1ced-1fac169831dc|e:1777805345244|c:1777802289225|l:1777803545244\"}"}, {"name": "isZendeskScriptLoaded", "value": "true"}, {"name": "ucData", "value": "{\"gcm\":{\"adsDataRedaction\":true,\"adStorage\":\"denied\",\"adPersonalization\":\"denied\",\"adUserData\":\"denied\",\"analyticsStorage\":\"denied\"},\"consent\":{\"services\":{\"Xl0HIOViY\":{\"name\":\"Datadog Real User Monitoring\",\"consent\":true},\"HkPBYFofN\":{\"name\":\"Google Fonts\",\"consent\":true},\"R2gyvn3ugawW0t\":{\"name\":\"Google Hosted Libraries\",\"consent\":true},\"S1pcEj_jZX\":{\"name\":\"Google Maps\",\"consent\":true},\"XJGT8f-58\":{\"name\":\"Google Sign-In\",\"consent\":true},\"BJ59EidsWQ\":{\"name\":\"Google Tag Manager\",\"consent\":true},\"rJJjcVouoZ7\":{\"name\":\"gstatic.com\",\"consent\":true},\"H1Vl5NidjWX\":{\"name\":\"Usercentrics Consent Management Platform\",\"consent\":true},\"54s8nFgf\":{\"name\":\"Zendesk\",\"consent\":true},\"ko1w5PpFl\":{\"name\":\"Facebook Pixel\",\"consent\":false},\"twMyStLkn\":{\"name\":\"Google Ads Conversion Tracking\",\"consent\":false},\"87JYasXPF\":{\"name\":\"Google Analytics 4\",\"consent\":false},\"S1kgcNo_j-m\":{\"name\":\"Hotjar\",\"consent\":false},\"JQ2XQxIk\":{\"name\":\"LinkedIn Insight Tag\",\"consent\":false},\"rH1vNPCFR\":{\"name\":\"Sentry\",\"consent\":false}}},\"ui\":{\"language\":\"en\"}}"}, {"name": "ab.storage.ffLastRefreshAt.c36da9fe-8874-4c02-8a45-d9edace47cff", "value": "{\"v\":1777802289615}"}, {"name": "ZD-buid", "value": "88925bade3dc4c2a806922c0c2610dc7"}, {"name": "isZendeskChatAuthenticated", "value": "true"}, {"name": "zendeskAuthToken", "value": "eyJhbGciOiJIUzUxMiIsInR5cCI6IkpXVCIsImtpZCI6ImFwcF82NmQ4NTIzOWM1NzkwMzhlYzYxZGYwOTEifQ.eyJzY29wZSI6InVzZXIiLCJleHRlcm5hbF9pZCI6IkdZR1NVUFBMSUVSQUNDT1VOVDEwNzE4MDgiLCJlbWFpbF92ZXJpZmllZCI6dHJ1ZSwiaWF0IjoxNzc3ODAzNTQ1LCJqdGkiOiI1NmM5NDNlYy1jMDJjLTQ2MTUtODdhMS04NDQ5ZTY2MjJlOGIiLCJuYW1lIjoiTmlsZSBDcnlzdGFsIiwiZW1haWwiOiJuaWxlLmNyeXN0YWwuYm9va2luZ0BnbWFpbC5jb20ifQ.m-mP4HD9rslOvP61LwT1ZNv7iJZUe6k4xelLt8UpQQkMVlV1E8CSq6lYSO3jGJu2KiZPnS35eT8yFutg_b66bA"}, {"name": "zendeskChatStatus", "value": "unknown"}, {"name": "sentinel_data_obj_sent", "value": "{\"734946\":true}"}, {"name": "66d0858efe670c71fc7df867.appUserId", "value": "69c466fc4b23483749e0f871"}, {"name": "statsig.last_modified_time.evaluations", "value": "{\"statsig.cached.evaluations.234216753\":1777803383405,\"statsig.cached.evaluations.2180267028\":1777803544945}"}, {"name": "66d0858efe670c71fc7df867.surname", "value": "Crystal"}, {"name": "66d0858efe670c71fc7df867.conversationStartedAt", "value": "\"2026-05-03T10:19:06.454Z\""}, {"name": "ab.storage.lastReqToEndpoint.c36da9fe-8874-4c02-8a45-d9edace47cff", "value": "{\"v\":{\"d\":1777803545245,\"ff\":1777802289235}}"}, {"name": "ab.storage.session_id_for_cached_metadata.c36da9fe-8874-4c02-8a45-d9edace47cff", "value": "{\"v\":\"f54d535b-3877-9828-1ced-1fac169831dc\"}"}, {"name": "66d0858efe670c71fc7df867.email", "value": "nile.crystal.booking@gmail.com"}, {"name": "ab.storage.globalRateLimitCurrentTokenCount.c36da9fe-8874-4c02-8a45-d9edace47cff", "value": "{\"v\":24}"}, {"name": "ab.storage.sdk_metadata.c36da9fe-8874-4c02-8a45-d9edace47cff", "value": "{\"v\":[\"npm\"]}"}, {"name": "statsig.cached.evaluations.2180267028", "value": "{\"source\":\"NetworkNotModified\",\"data\":\"{\\\"feature_gates\\\":{\\\"1357805670\\\":{\\\"name\\\":\\\"1357805670\\\",\\\"value\\\":false,\\\"rule_id\\\":\\\"1roFVFlnaR2vBKPULmVQUJ:0.00:1\\\",\\\"id_type\\\":\\\"supplierId\\\",\\\"secondary_exposures\\\":[]}},\\\"dynamic_configs\\\":{\\\"1051049071\\\":{\\\"name\\\":\\\"1051049071\\\",\\\"value\\\":{},\\\"rule_id\\\":\\\"inlineTargetingRules\\\",\\\"group\\\":\\\"inlineTargetingRules\\\",\\\"is_device_based\\\":false,\\\"id_type\\\":\\\"userID\\\",\\\"is_experiment_active\\\":true,\\\"is_user_in_experiment\\\":false,\\\"secondary_exposures\\\":[]}},\\\"layer_configs\\\":{},\\\"sdkParams\\\":{},\\\"has_updates\\\":true,\\\"generator\\\":\\\"scrapi-nest\\\",\\\"time\\\":1777718638740,\\\"company_lcut\\\":1777718638740,\\\"evaluated_keys\\\":{\\\"userID\\\":\\\"QVSMG91M55VYJ4BIKBR2N3I1QOWOVP0E\\\",\\\"stableID\\\":\\\"eb4947c0-04db-4633-b5bf-efa1fd797600\\\",\\\"customIDs\\\":{\\\"customerId\\\":\\\"734946\\\"}},\\\"hash_used\\\":\\\"djb2\\\",\\\"derived_fields\\\":{\\\"ip\\\":\\\"57.151.123.251\\\",\\\"country\\\":\\\"US\\\",\\\"locale\\\":\\\"en-US\\\",\\\"browserName\\\":\\\"Chrome\\\",\\\"browserVersion\\\":\\\"120.0.0\\\",\\\"osName\\\":\\\"Windows\\\",\\\"osVersion\\\":\\\"10.0.0\\\",\\\"browser_name\\\":\\\"Chrome\\\",\\\"browser_version\\\":\\\"120.0.0\\\",\\\"os_name\\\":\\\"Windows\\\",\\\"os_version\\\":\\\"10.0.0\\\"},\\\"hashed_sdk_key_used\\\":\\\"1729579267\\\",\\\"can_record_session\\\":false,\\\"recording_blocked\\\":false,\\\"session_recording_rate\\\":1,\\\"auto_capture_settings\\\":{\\\"disabled_events\\\":{\\\"page_view\\\":true,\\\"page_view_end\\\":true,\\\"click\\\":true,\\\"scroll\\\":true,\\\"session_start\\\":true,\\\"form_submit\\\":true,\\\"error\\\":true,\\\"dead_click\\\":true,\\\"rage_click\\\":true,\\\"copy\\\":true}},\\\"param_stores\\\":{},\\\"target_app_used\\\":\\\"supplier-portal\\\",\\\"full_checksum\\\":\\\"3912422369\\\"}\",\"receivedAt\":1777803544944,\"stableID\":\"eb4947c0-04db-4633-b5bf-efa1fd797600\",\"fullUserHash\":\"2825252301\"}"}, {"name": "ab.storage.deviceId.c36da9fe-8874-4c02-8a45-d9edace47cff", "value": "{\"v\":\"g:c1b12ea3-b2f2-479f-41bd-329e870e6e00|e:undefined|c:1777793469704|l:1777802289225\"}"}, {"name": "ucString", "value": "N4IgbgpgTgzglgewHYgFwEYA0ICucBq08yaIAzAHTroCcFADCNgMbIAuUCANl9AJIATUgDZ6AM2ZkA7ACZ0EZgFYpi9MwCGUmorHpFADkX11+gEamyGqcMVzFZUzLJiBwgRAAsZmerLqx9Kb6HhD2NFJMIFzqSADmOOqxEKQQKNgwEGxscHFooGwAngAOyaggAOIAIgAKAEqRcEJlpjBFSAC0ABoAtgCCAJoIAB7dMABSkZCwiChl6FIUC2Q0IAC+2DhFAupsEAK9bGjzUic0ZB7Cl7QbWzt7AEIFpMiVqQW9PADK0GBwzBAwSLMKAQO77Q4YE6nc4GC4ybAggCOeBBTTE6i4GXSbB2OEBZV6ABlCQB9SoAUQAcnxyZVIoUSqRyZ1qoS+ABhPgAFUiAAt1DBeaQaKZFIpNIYJPptgJ0MIPGQyIEIGIfGR5nKNMIICL1LQxMoBA4pAJwqFaIoBPQBAIQkp7JEMlBfv9BPiANoAXWwsSKzE+cFiSAxaHRmIg2Byuyg6mY2RIZTx0DWQA=="}, {"name": "ab.storage.lastSdkReq.c36da9fe-8874-4c02-8a45-d9edace47cff", "value": "{\"v\":1777803545245}"}, {"name": "ab.storage.serverConfig.c36da9fe-8874-4c02-8a45-d9edace47cff", "value": "{\"v\":{\"s\":\"5.1.1\",\"l\":1774361172,\"e\":[],\"a\":[\"20250129_commission_is_tour_6\",\"202501_activ_tours_3defects_campaign\",\"accounts\",\"attributesMap\",\"completedness\",\"dev_tours\",\"exampleArr\",\"exampleArr10\",\"exampleArr2\",\"mql_activities>tours_online\"],\"p\":[],\"m\":21600,\"v\":\"BGWjRIY5UQ_emQBXbcJdUyrKz0N2vDTT_DuZQbnoHe6E6gTIA9m6un60Y-X3Ip0ifxBHjK7oPoHiodrrZwMXr9c=\",\"c\":{\"enabled\":true},\"f\":{\"enabled\":true,\"refresh_rate_limit\":300},\"grl\":{\"capacity\":30,\"enabled\":true,\"endpoint_overrides\":{\"banners/sync\":{\"capacity\":5,\"refill_rate\":180},\"content_cards/sync\":{\"capacity\":5,\"refill_rate\":10},\"push/redeliver\":{\"capacity\":1,\"refill_rate\":180}},\"refill_rate\":30}}}"}, {"name": "zendeskExternalId", "value": "GYGSUPPLIERACCOUNT1071808"}, {"name": "ab.storage.ff.sessionId.c36da9fe-8874-4c02-8a45-d9edace47cff", "value": "{\"v\":\"f54d535b-3877-9828-1ced-1fac169831dc\"}"}, {"name": "sidebar-onboarding-seen", "value": "true"}, {"name": "statsig.cached.evaluations.234216753", "value": "{\"source\":\"NetworkNotModified\",\"data\":\"{\\\"feature_gates\\\":{\\\"1357805670\\\":{\\\"name\\\":\\\"1357805670\\\",\\\"value\\\":false,\\\"rule_id\\\":\\\"1roFVFlnaR2vBKPULmVQUJ:0.00:1\\\",\\\"id_type\\\":\\\"supplierId\\\",\\\"secondary_exposures\\\":[]}},\\\"dynamic_configs\\\":{\\\"1051049071\\\":{\\\"name\\\":\\\"1051049071\\\",\\\"value\\\":{},\\\"rule_id\\\":\\\"inlineTargetingRules\\\",\\\"group\\\":\\\"inlineTargetingRules\\\",\\\"is_device_based\\\":false,\\\"id_type\\\":\\\"userID\\\",\\\"is_experiment_active\\\":true,\\\"is_user_in_experiment\\\":false,\\\"secondary_exposures\\\":[]}},\\\"layer_configs\\\":{},\\\"sdkParams\\\":{},\\\"has_updates\\\":true,\\\"generator\\\":\\\"scrapi-nest\\\",\\\"time\\\":1777718638740,\\\"company_lcut\\\":1777718638740,\\\"evaluated_keys\\\":{\\\"userID\\\":\\\"QVSMG91M55VYJ4BIKBR2N3I1QOWOVP0E\\\",\\\"stableID\\\":\\\"eb4947c0-04db-4633-b5bf-efa1fd797600\\\"},\\\"hash_used\\\":\\\"djb2\\\",\\\"derived_fields\\\":{\\\"ip\\\":\\\"57.151.123.251\\\",\\\"country\\\":\\\"US\\\",\\\"locale\\\":\\\"en-US\\\",\\\"browserName\\\":\\\"Chrome\\\",\\\"browserVersion\\\":\\\"120.0.0\\\",\\\"osName\\\":\\\"Windows\\\",\\\"osVersion\\\":\\\"10.0.0\\\",\\\"browser_name\\\":\\\"Chrome\\\",\\\"browser_version\\\":\\\"120.0.0\\\",\\\"os_name\\\":\\\"Windows\\\",\\\"os_version\\\":\\\"10.0.0\\\"},\\\"hashed_sdk_key_used\\\":\\\"1729579267\\\",\\\"can_record_session\\\":false,\\\"recording_blocked\\\":false,\\\"session_recording_rate\\\":1,\\\"auto_capture_settings\\\":{\\\"disabled_events\\\":{\\\"page_view\\\":true,\\\"page_view_end\\\":true,\\\"click\\\":true,\\\"scroll\\\":true,\\\"session_start\\\":true,\\\"form_submit\\\":true,\\\"error\\\":true,\\\"dead_click\\\":true,\\\"rage_click\\\":true,\\\"copy\\\":true}},\\\"param_stores\\\":{},\\\"target_app_used\\\":\\\"supplier-portal\\\",\\\"full_checksum\\\":\\\"3912422369\\\"}\",\"receivedAt\":1777803383405,\"stableID\":\"eb4947c0-04db-4633-b5bf-efa1fd797600\",\"fullUserHash\":\"2344168748\"}"}, {"name": "uc:analytics:firedEvents:bspn-XmAYoxmsJ", "value": "[\"CMP_ELIGIBLE\",\"CMP_SHOWN\",\"DENY_ALL\"]"}, {"name": "statsig.session_id.3726937202", "value": "{\"sessionID\":\"bb4ea727-b707-4847-951e-288d0fe2e9bd\",\"startTime\":1777802239028,\"lastUpdate\":1777803544859}"}, {"name": "66d0858efe670c71fc7df867.givenName", "value": "Nile"}, {"name": "ab.storage.ff.c36da9fe-8874-4c02-8a45-d9edace47cff", "value": "{\"v\":{}}"}, {"name": "ab.storage.triggers.ts.c36da9fe-8874-4c02-8a45-d9edace47cff", "value": "{\"v\":1777802289633}"}]}, {"origin": "https://web.cmp.usercentrics.eu", "localStorage": [{"name": "ucData_bspn-XmAYoxmsJ", "value": "{\"ucString\":\"N4IgbgpgTgzglgewHYgFwEYA0ICucBq08yaIAzAHTroCcFADCNgMbIAuUCANl9AJIATUgDZ6AM2ZkA7ACZ0EZgFYpi9MwCGUmorHpFADkX11+gEamyGqcMVzFZUzLJiBwgRAAsZmerLqx9Kb6HhD2NFJMIFzqSADmOOqxEKQQKNgwEGxscHFooGwAngAOyaggAOIAIgAKAEqRcEJlpjBFSAC0ABoAtgCCAJoIAB7dMABSkZCwiChl6FIUC2Q0IAC+2DhFAupsEAK9bGjzUic0ZB7Cl7QbWzt7AEIFpMiVqQW9PADK0GBwzBAwSLMKAQO77Q4YE6nc4GC4ybAggCOeBBTTE6i4GXSbB2OEBZV6ABlCQB9SoAUQAcnxyZVIoUSqRyZ1qoS+ABhPgAFUiAAt1DBeaQaKZFIpNIYJPptgJ0MIPGQyIEIGIfGR5nKNMIICL1LQxMoBA4pAJwqFaIoBPQBAIQkp7JEMlBfv9BPiANoAXWwsSKzE+cFiSAxaHRmIg2Byuyg6mY2RIZTx0DWQA==\"}"}]}, {"origin": "https://cluster-de.withpersona.com", "localStorage": [{"name": "_vid_t", "value": "FcjVNmFyH+jBRkVIiywtP0jmg/8UTx0GlAlOml4hddyrVa7+uGSkUq9LKylOVy2RfjhcNxbJXj84KkUPfhUvLRE1OSasALySE6DQyRm/tX5OKRBevQ=="}]}]}